class Test2 extends Test1
filename		Test2
compiled from		test2.java
compiler version	46.0
access flags		32
constant pool		21 entries
ACC_SUPER flag		true

Attribute(s):
	SourceFile(test2.java)

3 methods:
	void <init>()
	public void verander()
	public int getsuper()

void <init>()
Code(max_stack = 1, max_locals = 1, code_length = 5)
0:    aload_0
1:    invokespecial	Test1.<init> ()V (1)
4:    return

Attribute(s) = 
LineNumber(0, 5), LineNumber(4, 7)

public void verander()
Code(max_stack = 2, max_locals = 1, code_length = 11)
0:    aload_0
1:    iconst_4
2:    putfield		Test2.testvar I (2)
5:    aload_0
6:    iconst_2
7:    putfield		Test1.testvar I (3)
10:   return

Attribute(s) = 
LineNumber(0, 10), LineNumber(5, 11), LineNumber(10, 12)

public int getsuper()
Code(max_stack = 1, max_locals = 1, code_length = 5)
0:    aload_0
1:    getfield		Test1.testvar I (3)
4:    ireturn

Attribute(s) = 
LineNumber(0, 15)

Ooops
