class Testapp extends java.lang.Object
filename		Testapp
compiled from		testapp.java
compiler version	46.0
access flags		32
constant pool		21 entries
ACC_SUPER flag		true

Attribute(s):
	SourceFile(testapp.java)

2 methods:
	void <init>()
	public static void main(String[] arg0)

void <init>()
Code(max_stack = 1, max_locals = 1, code_length = 5)
0:    aload_0
1:    invokespecial	java.lang.Object.<init> ()V (1)
4:    return

Attribute(s) = 
LineNumber(0, 1)

public static void main(String[] arg0)
Code(max_stack = 2, max_locals = 2, code_length = 13)
0:    new		<Test2> (2)
3:    dup
4:    invokespecial	Test2.<init> ()V (3)
7:    astore_1
8:    aload_1
9:    invokevirtual	Test2.verander ()V (4)
12:   return

Attribute(s) = 
LineNumber(0, 6), LineNumber(8, 8), LineNumber(12, 11)

Ooops
